pps_emu/__init__.py
pps_emu-2.22.dist-info/LICENSE
pps_emu-2.22.dist-info/METADATA
pps_emu-2.22.dist-info/WHEEL
pps_emu-2.22.dist-info/top_level.txt
pps_emu-2.22.dist-info/RECORD
