Metadata-Version: 2.1
Name: pps-emu
Version: 2.22
Summary: A software based Raspberry Pi type simulator to aid in teaching Python
Home-page: https://github.com/chuckwhealton/pps_emu
Author: Charles R. Whealton
Author-email: chuck@dtcc.edu
License: UNKNOWN
Keywords: ITN 160
Platform: UNKNOWN
Classifier: Development Status :: 4 - Beta
Classifier: Topic :: Software Development :: Build Tools
Classifier: License :: OSI Approved :: MIT License
Classifier: Programming Language :: Python :: 3
Classifier: Operating System :: OS Independent
Requires-Dist: pps-gui
